jsonclasses_sanic/__init__.py
jsonclasses_sanic/decorators.py
jsonclasses_sanic/exceptions.py
jsonclasses_sanic/middlewares.py
jsonclasses_sanic/response.py
jsonclasses_sanic/utils.py
jsonclasses_sanic-2.3.2.dist-info/LICENSE
jsonclasses_sanic-2.3.2.dist-info/METADATA
jsonclasses_sanic-2.3.2.dist-info/WHEEL
jsonclasses_sanic-2.3.2.dist-info/top_level.txt
jsonclasses_sanic-2.3.2.dist-info/RECORD
