Metadata-Version: 2.1
Name: jsonclasses-sanic
Version: 2.3.2
Summary: JSON Classes integration with sanic.
Home-page: https://github.com/fillmula/jsonclasses-sanic
Author: Fillmula Inc.
Author-email: wiosoftvictor@163.com
License: MIT
Platform: UNKNOWN
Requires-Python: >=3.9
